{
  "schema_version": 1,
  "provider": "gold_api_com",
  "provider_url": "https://gold-api.com/",
  "source_type": "spot_reference",
  "raw_symbol": "XAU",
  "quote_currency": "USD",
  "xau_usd_per_oz": 3989.0,
  "usd_per_gram_24k": 128.249328,
  "aed_per_gram_24k": 470.9957,
  "aed_peg": 3.6725,
  "timestamp_utc": "2026-06-25T08:00:10Z",
  "timestamp_source": "provider",
  "fetched_at_utc": "2026-06-25T08:00:15Z",
  "freshness_seconds": 5,
  "max_freshness_seconds": 900,
  "is_fresh": true,
  "is_fallback": false,
  "bid": null,
  "ask": null,
  "spread": null,
  "provider_response_time_ms": 527,
  "raw_provider_confidence": null,
  "notes": "gold-api.com spot/reference price. Monitored with provider fallback.",
  "source": "gold_api_com",
  "source_updated_at_gmt": "25-06-2026 08:00:10 am",
  "gold": {
    "ounce_usd": 3989.0,
    "ounce_aed": 14649.6,
    "gram_aed": 471.0,
    "day_low_usd": null,
    "day_high_usd": null,
    "ask_usd": 3989.0,
    "bid_usd": 3989.0
  },
  "karats_aed_per_gram": {
    "24k": 471.0,
    "22k": 431.75,
    "21k": 412.12,
    "18k": 353.25
  },
  "status": "ok"
}
