{
  "schema_version": 1,
  "provider": "gold_api_com",
  "provider_url": "https://gold-api.com/",
  "source_type": "spot_reference",
  "raw_symbol": "XAU",
  "quote_currency": "USD",
  "xau_usd_per_oz": 4107.5,
  "usd_per_gram_24k": 132.059192,
  "aed_per_gram_24k": 484.9874,
  "aed_peg": 3.6725,
  "timestamp_utc": "2026-07-08T01:24:11Z",
  "timestamp_source": "provider",
  "fetched_at_utc": "2026-07-08T01:24:22Z",
  "freshness_seconds": 11,
  "max_freshness_seconds": 900,
  "is_fresh": true,
  "is_fallback": false,
  "bid": null,
  "ask": null,
  "spread": null,
  "provider_response_time_ms": 458,
  "raw_provider_confidence": null,
  "notes": "gold-api.com spot/reference price. Monitored with provider fallback.",
  "source": "gold_api_com",
  "source_updated_at_gmt": "08-07-2026 01:24:11 am",
  "gold": {
    "ounce_usd": 4107.5,
    "ounce_aed": 15084.79,
    "gram_aed": 484.99,
    "day_low_usd": null,
    "day_high_usd": null,
    "ask_usd": 4107.5,
    "bid_usd": 4107.5
  },
  "karats_aed_per_gram": {
    "24k": 484.99,
    "22k": 444.57,
    "21k": 424.36,
    "18k": 363.74
  },
  "status": "ok"
}
