{
  "schema_version": 1,
  "provider": "gold_api_com",
  "provider_url": "https://gold-api.com/",
  "source_type": "spot_reference",
  "raw_symbol": "XAU",
  "quote_currency": "USD",
  "xau_usd_per_oz": 3970.3,
  "usd_per_gram_24k": 127.648111,
  "aed_per_gram_24k": 468.7877,
  "aed_peg": 3.6725,
  "timestamp_utc": "2026-07-01T07:44:52Z",
  "timestamp_source": "provider",
  "fetched_at_utc": "2026-07-01T07:45:18Z",
  "freshness_seconds": 26,
  "max_freshness_seconds": 900,
  "is_fresh": true,
  "is_fallback": false,
  "bid": null,
  "ask": null,
  "spread": null,
  "provider_response_time_ms": 506,
  "raw_provider_confidence": null,
  "notes": "gold-api.com spot/reference price. Monitored with provider fallback.",
  "source": "gold_api_com",
  "source_updated_at_gmt": "01-07-2026 07:44:52 am",
  "gold": {
    "ounce_usd": 3970.3,
    "ounce_aed": 14580.93,
    "gram_aed": 468.79,
    "day_low_usd": null,
    "day_high_usd": null,
    "ask_usd": 3970.3,
    "bid_usd": 3970.3
  },
  "karats_aed_per_gram": {
    "24k": 468.79,
    "22k": 429.72,
    "21k": 410.19,
    "18k": 351.59
  },
  "status": "ok"
}
