{
  "schema_version": 1,
  "provider": "gold_api_com",
  "provider_url": "https://gold-api.com/",
  "source_type": "spot_reference",
  "raw_symbol": "XAU",
  "quote_currency": "USD",
  "xau_usd_per_oz": 4481.8999,
  "usd_per_gram_24k": 144.096428,
  "aed_per_gram_24k": 529.1941,
  "aed_peg": 3.6725,
  "timestamp_utc": "2026-06-04T20:00:05Z",
  "timestamp_source": "provider",
  "fetched_at_utc": "2026-06-04T20:00:18Z",
  "freshness_seconds": 13,
  "max_freshness_seconds": 900,
  "is_fresh": true,
  "is_fallback": false,
  "bid": null,
  "ask": null,
  "spread": null,
  "provider_response_time_ms": 328,
  "raw_provider_confidence": null,
  "notes": "gold-api.com spot/reference price. Monitored with provider fallback.",
  "source": "gold_api_com",
  "source_updated_at_gmt": "04-06-2026 08:00:05 pm",
  "gold": {
    "ounce_usd": 4481.9,
    "ounce_aed": 16459.78,
    "gram_aed": 529.19,
    "day_low_usd": null,
    "day_high_usd": null,
    "ask_usd": 4481.9,
    "bid_usd": 4481.9
  },
  "karats_aed_per_gram": {
    "24k": 529.19,
    "22k": 485.09,
    "21k": 463.04,
    "18k": 396.9
  },
  "status": "ok"
}
