{
  "schema_version": 1,
  "provider": "gold_api_com",
  "provider_url": "https://gold-api.com/",
  "source_type": "spot_reference",
  "raw_symbol": "XAU",
  "quote_currency": "USD",
  "xau_usd_per_oz": 4127.2998,
  "usd_per_gram_24k": 132.69577,
  "aed_per_gram_24k": 487.3252,
  "aed_peg": 3.6725,
  "timestamp_utc": "2026-07-22T12:18:06Z",
  "timestamp_source": "provider",
  "fetched_at_utc": "2026-07-22T12:18:23Z",
  "freshness_seconds": 17,
  "max_freshness_seconds": 900,
  "is_fresh": true,
  "is_fallback": false,
  "bid": null,
  "ask": null,
  "spread": null,
  "provider_response_time_ms": 725,
  "raw_provider_confidence": null,
  "notes": "gold-api.com spot/reference price. Monitored with provider fallback.",
  "source": "gold_api_com",
  "source_updated_at_gmt": "22-07-2026 12:18:06 pm",
  "gold": {
    "ounce_usd": 4127.3,
    "ounce_aed": 15157.51,
    "gram_aed": 487.33,
    "day_low_usd": null,
    "day_high_usd": null,
    "ask_usd": 4127.3,
    "bid_usd": 4127.3
  },
  "karats_aed_per_gram": {
    "24k": 487.33,
    "22k": 446.71,
    "21k": 426.41,
    "18k": 365.49
  },
  "status": "ok"
}
