{
  "schema_version": 1,
  "provider": "gold_api_com",
  "provider_url": "https://gold-api.com/",
  "source_type": "spot_reference",
  "raw_symbol": "XAU",
  "quote_currency": "USD",
  "xau_usd_per_oz": 4092.6001,
  "usd_per_gram_24k": 131.580149,
  "aed_per_gram_24k": 483.2281,
  "aed_peg": 3.6725,
  "timestamp_utc": "2026-07-23T08:36:20Z",
  "timestamp_source": "provider",
  "fetched_at_utc": "2026-07-23T08:36:22Z",
  "freshness_seconds": 2,
  "max_freshness_seconds": 900,
  "is_fresh": true,
  "is_fallback": false,
  "bid": null,
  "ask": null,
  "spread": null,
  "provider_response_time_ms": 369,
  "raw_provider_confidence": null,
  "notes": "gold-api.com spot/reference price. Monitored with provider fallback.",
  "source": "gold_api_com",
  "source_updated_at_gmt": "23-07-2026 08:36:20 am",
  "gold": {
    "ounce_usd": 4092.6,
    "ounce_aed": 15030.07,
    "gram_aed": 483.23,
    "day_low_usd": null,
    "day_high_usd": null,
    "ask_usd": 4092.6,
    "bid_usd": 4092.6
  },
  "karats_aed_per_gram": {
    "24k": 483.23,
    "22k": 442.96,
    "21k": 422.82,
    "18k": 362.42
  },
  "status": "ok"
}
