{
  "schema_version": 1,
  "provider": "gold_api_com",
  "provider_url": "https://gold-api.com/",
  "source_type": "spot_reference",
  "raw_symbol": "XAU",
  "quote_currency": "USD",
  "xau_usd_per_oz": 4038.1001,
  "usd_per_gram_24k": 129.827933,
  "aed_per_gram_24k": 476.7931,
  "aed_peg": 3.6725,
  "timestamp_utc": "2026-07-21T03:00:03Z",
  "timestamp_source": "provider",
  "fetched_at_utc": "2026-07-21T03:00:18Z",
  "freshness_seconds": 15,
  "max_freshness_seconds": 900,
  "is_fresh": true,
  "is_fallback": false,
  "bid": null,
  "ask": null,
  "spread": null,
  "provider_response_time_ms": 450,
  "raw_provider_confidence": null,
  "notes": "gold-api.com spot/reference price. Monitored with provider fallback.",
  "source": "gold_api_com",
  "source_updated_at_gmt": "21-07-2026 03:00:03 am",
  "gold": {
    "ounce_usd": 4038.1,
    "ounce_aed": 14829.92,
    "gram_aed": 476.79,
    "day_low_usd": null,
    "day_high_usd": null,
    "ask_usd": 4038.1,
    "bid_usd": 4038.1
  },
  "karats_aed_per_gram": {
    "24k": 476.79,
    "22k": 437.06,
    "21k": 417.19,
    "18k": 357.59
  },
  "status": "ok"
}
