{
  "schema_version": 1,
  "provider": "gold_api_com",
  "provider_url": "https://gold-api.com/",
  "source_type": "spot_reference",
  "raw_symbol": "XAU",
  "quote_currency": "USD",
  "xau_usd_per_oz": 4664.2998,
  "usd_per_gram_24k": 149.960721,
  "aed_per_gram_24k": 550.7307,
  "aed_peg": 3.6725,
  "timestamp_utc": "2026-05-11T09:46:56Z",
  "timestamp_source": "provider",
  "fetched_at_utc": "2026-05-11T09:47:40Z",
  "freshness_seconds": 44,
  "max_freshness_seconds": 900,
  "is_fresh": true,
  "is_fallback": false,
  "bid": null,
  "ask": null,
  "spread": null,
  "provider_response_time_ms": 278,
  "raw_provider_confidence": null,
  "notes": "gold-api.com spot/reference price. Monitored with provider fallback.",
  "source": "gold_api_com",
  "source_updated_at_gmt": "11-05-2026 09:46:56 am",
  "gold": {
    "ounce_usd": 4664.3,
    "ounce_aed": 17129.64,
    "gram_aed": 550.73,
    "day_low_usd": null,
    "day_high_usd": null,
    "ask_usd": 4664.3,
    "bid_usd": 4664.3
  },
  "karats_aed_per_gram": {
    "24k": 550.73,
    "22k": 504.84,
    "21k": 481.89,
    "18k": 413.05
  },
  "status": "ok"
}
