{
  "schema_version": 1,
  "provider": "gold_api_com",
  "provider_url": "https://gold-api.com/",
  "source_type": "spot_reference",
  "raw_symbol": "XAU",
  "quote_currency": "USD",
  "xau_usd_per_oz": 4115.2998,
  "usd_per_gram_24k": 132.309961,
  "aed_per_gram_24k": 485.9083,
  "aed_peg": 3.6725,
  "timestamp_utc": "2026-07-22T09:54:35Z",
  "timestamp_source": "provider",
  "fetched_at_utc": "2026-07-22T09:54:41Z",
  "freshness_seconds": 6,
  "max_freshness_seconds": 900,
  "is_fresh": true,
  "is_fallback": false,
  "bid": null,
  "ask": null,
  "spread": null,
  "provider_response_time_ms": 212,
  "raw_provider_confidence": null,
  "notes": "gold-api.com spot/reference price. Monitored with provider fallback.",
  "source": "gold_api_com",
  "source_updated_at_gmt": "22-07-2026 09:54:35 am",
  "gold": {
    "ounce_usd": 4115.3,
    "ounce_aed": 15113.44,
    "gram_aed": 485.91,
    "day_low_usd": null,
    "day_high_usd": null,
    "ask_usd": 4115.3,
    "bid_usd": 4115.3
  },
  "karats_aed_per_gram": {
    "24k": 485.91,
    "22k": 445.42,
    "21k": 425.17,
    "18k": 364.43
  },
  "status": "ok"
}
