{
  "source": "goldpricez.com",
  "fetched_at_utc": "2026-04-27T11:59:30Z",
  "source_updated_at_gmt": "27-04-2026 11:59:28 am",
  "currency_primary": "AED",
  "gold": {
    "ounce_usd": 4705.18,
    "ounce_aed": 17284.48,
    "gram_aed": 554.83,
    "kg_aed": 555708.16,
    "tola_india_aed": 6481.68,
    "ask_usd": 4705.18,
    "bid_usd": 4705.18,
    "day_low_usd": 4671.8,
    "day_high_usd": 4730.45
  },
  "silver": {
    "ounce_usd": 0.0,
    "gram_aed": 0.0
  },
  "karats_aed_per_gram": {
    "24k": 554.83,
    "22k": 508.61,
    "21k": 485.48,
    "18k": 416.12
  },
  "status": "ok",
  "notes": "Spot/reference prices. Not UAE retail or jewelry shop prices."
}
