{
  "source": "goldpricez.com",
  "fetched_at_utc": "2026-04-25T07:46:08Z",
  "source_updated_at_gmt": "25-04-2026 07:45:59 am",
  "currency_primary": "AED",
  "gold": {
    "ounce_usd": 4708.51,
    "ounce_aed": 17294.36,
    "gram_aed": 555.15,
    "kg_aed": 556025.75,
    "tola_india_aed": 6485.38,
    "ask_usd": 4708.51,
    "bid_usd": 4708.51,
    "day_low_usd": 4708.49,
    "day_high_usd": 4709.25
  },
  "silver": {
    "ounce_usd": 0.0,
    "gram_aed": 0.0
  },
  "karats_aed_per_gram": {
    "24k": 555.15,
    "22k": 508.91,
    "21k": 485.76,
    "18k": 416.36
  },
  "status": "ok",
  "notes": "Spot/reference prices. Not UAE retail or jewelry shop prices."
}
