{
  "schema_version": 1,
  "provider": "gold_api_com",
  "provider_url": "https://gold-api.com/",
  "source_type": "spot_reference",
  "raw_symbol": "XAU",
  "quote_currency": "USD",
  "xau_usd_per_oz": 4055.0,
  "usd_per_gram_24k": 130.371277,
  "aed_per_gram_24k": 478.7885,
  "aed_peg": 3.6725,
  "timestamp_utc": "2026-07-21T13:00:03Z",
  "timestamp_source": "provider",
  "fetched_at_utc": "2026-07-21T13:00:29Z",
  "freshness_seconds": 26,
  "max_freshness_seconds": 900,
  "is_fresh": true,
  "is_fallback": false,
  "bid": null,
  "ask": null,
  "spread": null,
  "provider_response_time_ms": 514,
  "raw_provider_confidence": null,
  "notes": "gold-api.com spot/reference price. Monitored with provider fallback.",
  "source": "gold_api_com",
  "source_updated_at_gmt": "21-07-2026 01:00:03 pm",
  "gold": {
    "ounce_usd": 4055.0,
    "ounce_aed": 14891.99,
    "gram_aed": 478.79,
    "day_low_usd": null,
    "day_high_usd": null,
    "ask_usd": 4055.0,
    "bid_usd": 4055.0
  },
  "karats_aed_per_gram": {
    "24k": 478.79,
    "22k": 438.89,
    "21k": 418.94,
    "18k": 359.09
  },
  "status": "ok"
}
