{
  "schema_version": 1,
  "provider": "gold_api_com",
  "provider_url": "https://gold-api.com/",
  "source_type": "spot_reference",
  "raw_symbol": "XAU",
  "quote_currency": "USD",
  "xau_usd_per_oz": 3970.8999,
  "usd_per_gram_24k": 127.667396,
  "aed_per_gram_24k": 468.8585,
  "aed_peg": 3.6725,
  "timestamp_utc": "2026-06-30T03:53:49Z",
  "timestamp_source": "provider",
  "fetched_at_utc": "2026-06-30T03:54:13Z",
  "freshness_seconds": 24,
  "max_freshness_seconds": 900,
  "is_fresh": true,
  "is_fallback": false,
  "bid": null,
  "ask": null,
  "spread": null,
  "provider_response_time_ms": 96,
  "raw_provider_confidence": null,
  "notes": "gold-api.com spot/reference price. Monitored with provider fallback.",
  "source": "gold_api_com",
  "source_updated_at_gmt": "30-06-2026 03:53:49 am",
  "gold": {
    "ounce_usd": 3970.9,
    "ounce_aed": 14583.13,
    "gram_aed": 468.86,
    "day_low_usd": null,
    "day_high_usd": null,
    "ask_usd": 3970.9,
    "bid_usd": 3970.9
  },
  "karats_aed_per_gram": {
    "24k": 468.86,
    "22k": 429.79,
    "21k": 410.25,
    "18k": 351.64
  },
  "status": "ok"
}
