{
  "schema_version": 1,
  "last_tweet_id": "2079931077335122350",
  "last_tweet_time_utc": "2026-07-22T14:06:26Z",
  "last_tweet_text_hash": "db530c29db27c7d47d75a46bf802519f6ab5d8ed43bd107d9a1278d7910fdefb",
  "last_price_usd_oz": 4156.2002,
  "last_provider": "gold_api_com",
  "last_provider_timestamp_utc": "2026-07-22T14:06:06Z",
  "last_source_type": "spot_reference",
  "last_post_reason": "shortcut_price_moved",
  "last_trigger_source": "shortcut",
  "last_trigger_attempt_time_utc": "2026-07-22T14:06:26Z",
  "last_trigger_nonce": "none",
  "last_trigger_run_id": "29926950680",
  "last_trigger_run_attempt": "1"
}
