{
  "schema_version": 1,
  "last_tweet_id": null,
  "last_tweet_time_utc": "2026-06-29T14:06:15Z",
  "last_tweet_text_hash": "a65c7800c9a859b6e08375d6f80c115c68a724077fa5674ca4458a61a9d5bf4e",
  "last_price_usd_oz": 4028.1001,
  "last_provider": "gold_api_com",
  "last_provider_timestamp_utc": "2026-06-29T14:05:50Z",
  "last_source_type": "spot_reference",
  "last_post_reason": "shortcut_price_moved",
  "last_trigger_source": "shortcut",
  "last_trigger_attempt_time_utc": "2026-06-29T14:06:14Z",
  "last_trigger_nonce": "none",
  "last_trigger_run_id": "28377991548",
  "last_trigger_run_attempt": "1"
}
